kami_gsuite/__init__.py
kami_gsuite/constants.py
kami_gsuite/gsuite.py
kami_gsuite/kami_gdrive/__init__.py
kami_gsuite/kami_gdrive/gdrive.py
kami_gsuite/kami_gsheet/__init__.py
kami_gsuite/kami_gsheet/gsheet.py
kami_gsuite/prompts/prompts
kami_gsuite-0.1.0.dist-info/LICENSE
kami_gsuite-0.1.0.dist-info/METADATA
kami_gsuite-0.1.0.dist-info/WHEEL
kami_gsuite-0.1.0.dist-info/RECORD
