Metadata-Version: 2.1
Name: kami-gsuite
Version: 0.1.0
Summary: KAMI Python Lib to deal with gsuite issues google_drive, google_sheets, etc.
License: GNU
Author: Maicon de Menezes
Author-email: maicondmenezes@gmail.com
Requires-Python: >=3.10,<3.13
Classifier: Development Status :: 4 - Beta
Classifier: License :: Other/Proprietary License
Classifier: Natural Language :: English
Classifier: Programming Language :: Python :: 3
Classifier: Programming Language :: Python :: 3.10
Classifier: Programming Language :: Python :: 3.11
Classifier: Topic :: Communications :: File Sharing
Classifier: Topic :: Office/Business :: Office Suites
Requires-Dist: google-api-core (>=2.11.0,<3.0.0)
Requires-Dist: google-api-python-client (>=2.50.0,<3.0.0)
Requires-Dist: google-auth (>=2.7.0,<3.0.0)
Requires-Dist: google-auth-httplib2 (>=0.1.0,<0.2.0)
Requires-Dist: google-auth-oauthlib (>=0.5.2,<0.6.0)
Requires-Dist: googleapis-common-protos (>=1.56.2,<2.0.0)
Requires-Dist: kami-filemanager (>=0.1.0,<0.2.0)
Requires-Dist: kami-logging (>=0.2.0,<0.3.0)
Requires-Dist: pandas (>=2.1.1,<3.0.0)
Requires-Dist: python-dotenv (>=1.0.0,<2.0.0)
Project-URL: Bug Tracker, https://github.com/devkami/kami-uno-database/issues
Project-URL: Source, https://github.com/devkami/kami-uno-database
